authlit/__init__.py
authlit/config.py
authlit/utils.py
authlit/widgets.py
authlit/auth/__init__.py
authlit/auth/json_auth.py
authlit/auth/mongo_auth.py
authlit/auth/sql_auth.py
authlit/auth/yaml_auth.py
authlit/email/__init__.py
authlit/email/send_mail.py
authlit/examples/__init__.py
authlit/examples/simple_auth_ui.py
authlit/models/__init__.py
authlit/models/user.py
authlit/models/user_mongo.py
authlit/models/user_sql.py
authlit-0.1.3.dist-info/LICENSE
authlit-0.1.3.dist-info/METADATA
authlit-0.1.3.dist-info/WHEEL
authlit-0.1.3.dist-info/top_level.txt
authlit-0.1.3.dist-info/RECORD
