Metadata-Version: 2.1
Name: authlit
Version: 0.1.3
Summary: A streamlit library which provides a Login/Sign-Up UI with an option to reset password, also supports cookies.
Home-page: https://github.com/AGI-24/st-auth.git
Author: Badal Sahani
Author-email: badalsahani8381@gmail.com
Classifier: Programming Language :: Python :: 3
Classifier: License :: OSI Approved :: MIT License
Classifier: Operating System :: OS Independent
Requires-Python: >=3.6
License-File: LICENSE
Requires-Dist: streamlit
Requires-Dist: extra-streamlit-components
Requires-Dist: streamlit-option-menu
Requires-Dist: streamlit-cookies-manager
Requires-Dist: sqlalchemy
Requires-Dist: pymysql
Requires-Dist: pymongo
Requires-Dist: argon2-cffi
Requires-Dist: bcrypt
Requires-Dist: PyYAML
